project_one/file.py
project_one-0.1.0.dist-info/WHEEL
project_one-0.1.0.dist-info/METADATA
project_one-0.1.0.dist-info/RECORD
