Metadata-Version: 2.1
Name: project-one
Version: 0.1.0
Summary: Bamm_Files
Author: Aghyad Farrouh
Author-email: external.Aghyad.Farrouh@bosch.com
Requires-Python: >=3.10,<4.0
Classifier: Programming Language :: Python :: 3
Classifier: Programming Language :: Python :: 3.10
